InnoCleaner/__init__.py
InnoCleaner/cleaningTempFiles.py
InnoCleaner/cleaningUtility.py
InnoCleaner/fileClassDecleration.py
InnoCleaner/fileSortingOnExtension.py
InnoCleaner/findDuplicateFIles.py
InnoCleaner-1.0.17.dev1.dist-info/DESCRIPTION.rst
InnoCleaner-1.0.17.dev1.dist-info/METADATA
InnoCleaner-1.0.17.dev1.dist-info/RECORD
InnoCleaner-1.0.17.dev1.dist-info/WHEEL
InnoCleaner-1.0.17.dev1.dist-info/entry_points.txt
InnoCleaner-1.0.17.dev1.dist-info/metadata.json
InnoCleaner-1.0.17.dev1.dist-info/top_level.txt
