Metadata-Version: 2.0
Name: InnoCleaner
Version: 1.0.17.dev1
Summary: This is a CLI based cleaner utility for Unix based systems.
Home-page: https://github.com/Kush22/Cleaning-Sorting-Utility
Author: Kushagra Gupta
Author-email: kushagra.gupta@students.iiit.ac.in
License: MIT LICENSE
Keywords: Cleaning Utility Python-Tools
Platform: UNKNOWN
Classifier: Development Status :: 3 - Alpha
Classifier: Environment :: Console
Classifier: Intended Audience :: Developers
Classifier: License :: OSI Approved :: MIT License
Classifier: Programming Language :: Python :: 2.7
Classifier: Programming Language :: Python :: 3
Classifier: Programming Language :: Python :: 3.4
Classifier: Programming Language :: Python :: 3.5
Classifier: Programming Language :: Python :: 3.6
Requires-Python: >2.7
Requires-Dist: pathlib2
